{
  "name": "Chicken",
  "type": "miscgear",
  "img": "systems/sohl/assets/icons/miscgear.svg",
  "_id": "kD9vjtx5obhfT7l7",
  "system": {
    "shortcode": "chicken",
    "docUrl": "https://heroiclands.org/sohl/miscgear/chicken/",
    "actionDefs": [],
    "notes": "",
    "docHtml": "<p>Dressed poultry bought fresh from a market stall or slaughtered on the estate, delicate white meat prized for its tenderness. Households and taverns roast chicken whole or joint it for stewing; a single bird feeds a family or small gathering. The meat spoils quickly unless salted, smoked, or jerked, but freshly killed chicken is sweet and easily digested, preferred by the elderly and infirm.</p>\n",
    "quantity": 1,
    "weightBase": 1,
    "valueBase": 1.25,
    "qualityBase": 0,
    "durabilityBase": 0,
    "sharedWithCohortIds": [],
    "containerId": null,
    "isCarried": true,
    "isEquipped": false
  },
  "effects": [],
  "flags": {},
  "_stats": {
    "systemId": "sohl",
    "systemVersion": "0.6.0",
    "coreVersion": "14",
    "createdTime": 0,
    "modifiedTime": 0,
    "lastModifiedBy": "sohlbuilder00000"
  },
  "ownership": {
    "default": 0
  },
  "folder": "cHM58zOI1EcSG3cP",
  "_key": "!items!kD9vjtx5obhfT7l7"
}