{
  "name": "Shock",
  "type": "skill",
  "img": "systems/sohl/assets/icons/shock.svg",
  "_id": "BAHwD5BQSFtfbfGD",
  "system": {
    "shortcode": "shok",
    "docUrl": "https://heroiclands.org/sohl/skill/shock/",
    "actionDefs": [],
    "notes": "",
    "docHtml": "<p>Shock represents a combatant's physiological resilience to the trauma of violent injury—the ability to absorb a blow without being incapacitated by pain, blood loss, or the body's involuntary shutdown responses. It is tested whenever a character suffers significant physical damage in combat, determining whether they can continue to fight or are overcome by the shock of their wounds. Conditioning, body mass, and raw endurance all contribute to this capacity, which can mean the difference between staying on one's feet and collapsing from a wound that a tougher individual might shrug off.</p>\n",
    "subType": "combat",
    "skillBaseFormula": "@str, @end",
    "masteryLevelBase": 0,
    "improveFlag": false,
    "combatCategory": "none",
    "parentSkillCode": "",
    "initSkillMult": 3
  },
  "effects": [],
  "flags": {},
  "_stats": {
    "systemId": "sohl",
    "systemVersion": "0.6.0",
    "coreVersion": "14",
    "createdTime": 0,
    "modifiedTime": 0,
    "lastModifiedBy": "sohlbuilder00000"
  },
  "ownership": {
    "default": 0
  },
  "folder": "EphAMAfFhWBrJxyF",
  "_key": "!items!BAHwD5BQSFtfbfGD"
}