{
  "name": "Worsted Robe",
  "type": "armorgear",
  "img": "systems/sohl/assets/icons/robe.svg",
  "_id": "A0q2esETFwdkoFnC",
  "system": {
    "shortcode": "WRobe",
    "docUrl": "https://heroiclands.org/sohl/armorgear/worsted-robe/",
    "actionDefs": [],
    "notes": "",
    "docHtml": "<p>The Worsted Robe, made from tightly-spun wool fibers, offers both style and durability. It’s a versatile garment providing good insulation and resilience, suitable for a wide range of activities and weather conditions.</p>\n",
    "quantity": 1,
    "weightBase": 3.2,
    "valueBase": 190,
    "qualityBase": 0,
    "durabilityBase": 9,
    "sharedWithCohortIds": [],
    "containerId": null,
    "isCarried": true,
    "isEquipped": false,
    "material": "Cloth",
    "locations": {
      "flexible": [
        "lshldloc",
        "rshldloc",
        "lupaloc",
        "rupaloc",
        "lelbloc",
        "relbloc",
        "lfraloc",
        "rfraloc",
        "thrxloc",
        "abdmnloc",
        "plvisloc",
        "lthghloc",
        "rthghloc",
        "lkneeloc",
        "rkneeloc",
        "lcalfloc",
        "rcalfloc"
      ],
      "rigid": []
    },
    "protectionBase": {
      "blunt": 4,
      "edged": 8,
      "piercing": 5,
      "fire": 5
    },
    "encumbrance": 0
  },
  "effects": [],
  "flags": {},
  "_stats": {
    "systemId": "sohl",
    "systemVersion": "0.6.0",
    "coreVersion": "14",
    "createdTime": 0,
    "modifiedTime": 0,
    "lastModifiedBy": "sohlbuilder00000"
  },
  "ownership": {
    "default": 0
  },
  "folder": "gaC79vNjSo6VO6Ym",
  "_key": "!items!A0q2esETFwdkoFnC"
}